{
  "gitSyncId": "68f1ea66301c3b6f3e13c5f4_3bfc05e6-4ba5-4596-9b97-865b31e6e170",
  "id": "Dashboard_JS_WaSettings._getQueryGet",
  "pluginId": "js-plugin",
  "pluginType": "JS",
  "unpublishedAction": {
    "actionConfiguration": {
      "encodeParamsToggle": true,
      "jsArguments": [],
      "paginationType": "NONE",
      "timeoutInMillisecond": 10000
    },
    "collectionId": "Dashboard_JS_WaSettings",
    "confirmBeforeExecute": false,
    "datasource": {
      "isAutoGenerated": false,
      "name": "UNUSED_DATASOURCE",
      "pluginId": "js-plugin"
    },
    "dynamicBindingPathList": [
      {
        "key": "body"
      }
    ],
    "fullyQualifiedName": "JS_WaSettings._getQueryGet",
    "name": "_getQueryGet",
    "pageId": "Dashboard",
    "runBehaviour": "MANUAL",
    "userSetOnLoad": false
  }
}