{
  "gitSyncId": "68f1ea66301c3b6f3e13c5f4_b889d03a-adc0-411d-819f-36c29e474e36",
  "id": "Dashboard_JS_DataRefresh._sleep",
  "pluginId": "js-plugin",
  "pluginType": "JS",
  "unpublishedAction": {
    "actionConfiguration": {
      "encodeParamsToggle": true,
      "jsArguments": [
        {
          "name": "ms",
          "value": "{{250}}"
        }
      ],
      "paginationType": "NONE",
      "timeoutInMillisecond": 10000
    },
    "collectionId": "Dashboard_JS_DataRefresh",
    "confirmBeforeExecute": false,
    "datasource": {
      "isAutoGenerated": false,
      "name": "UNUSED_DATASOURCE",
      "pluginId": "js-plugin"
    },
    "dynamicBindingPathList": [
      {
        "key": "body"
      }
    ],
    "fullyQualifiedName": "JS_DataRefresh._sleep",
    "name": "_sleep",
    "pageId": "Dashboard",
    "runBehaviour": "MANUAL",
    "userSetOnLoad": false
  }
}