{
  "gitSyncId": "68f1ea66301c3b6f3e13c5f4_7833ee58-a76a-45ab-88ac-611bcd9fef3b",
  "id": "Dashboard_q_create_user",
  "pluginId": "postgres-plugin",
  "pluginType": "DB",
  "unpublishedAction": {
    "actionConfiguration": {
      "body": "WITH v AS (\n\tSELECT\n\t{{ appsmith.store.businessId }}::uuid                          AS bid,\n\tNULLIF(lower(trim({{ this.params.email || '' }}::text)), '')   AS email_norm,\n\t{{ this.params.new_pass }}::text                               AS pass_raw,\n\tupper(trim(COALESCE({{ this.params.role }}::text,'BARBER')))   AS role_raw,\n\tlower(trim(\n\t\tCOALESCE({{ this.params.created_by_email }},\n\t\t\t\t\t\t {{ appsmith.store.userEmail }},\n\t\t\t\t\t\t {{ appsmith.user.email }},\n\t\t\t\t\t\t '')\n\t))                                                             AS created_by_email\n),\nchk AS (\n\tSELECT\n\t-- 👇 en vez de regex complicada: solo que no sea NULL/vacío\n\t(email_norm IS NOT NULL)                                       AS ok_email,\n\t(length(pass_raw) >= 8)                                        AS ok_pass,\n\t(role_raw IN ('BARBER','ADMIN','OWNER','SUPERADMIN'))          AS ok_role\n\tFROM v\n),\ngo AS (\n\tSELECT 1\n\tFROM chk\n\tWHERE ok_email AND ok_pass AND ok_role\n),\n\ncreator AS (\n\tSELECT u.id AS created_by_id\n\tFROM \"User\" u, v\n\tWHERE u.\"businessId\" = v.bid\n\tAND lower(u.email) = v.created_by_email\n\tLIMIT 1\n),\nins AS (\n\tINSERT INTO \"User\" (\"businessId\", email, \"password\", role, \"createdBy\", \"createdByEmail\")\n\tSELECT v.bid, v.email_norm, crypt(v.pass_raw, gen_salt('bf')), v.role_raw,\n\tc.created_by_id, v.created_by_email\n\tFROM v\n\tJOIN go ON TRUE\n\tLEFT JOIN creator c ON TRUE\n\t-- sin nombrar constraint: deja que Postgres use el índice/unique que corresponda\n\tON CONFLICT DO NOTHING\n\tRETURNING id, email, role, \"createdBy\", \"createdByEmail\"\n)\nSELECT\n  (SELECT ok_email FROM chk) AS ok_email,\n  (SELECT ok_pass  FROM chk) AS ok_pass,\n  (SELECT ok_role  FROM chk) AS ok_role,\n  EXISTS (SELECT 1 FROM ins) AS inserted,\n  EXISTS (\n\t\tSELECT 1\n\t\tFROM \"User\" u, v\n\t\tWHERE lower(u.email) = v.email_norm\n\t\tAND u.\"businessId\" = v.bid\n\t) AS duplicate_email,\n  (SELECT to_jsonb(ins.*) FROM ins) AS row;\n",
      "encodeParamsToggle": true,
      "paginationType": "NONE",
      "pluginSpecifiedTemplates": [
        {
          "value": true
        }
      ],
      "timeoutInMillisecond": 10000
    },
    "confirmBeforeExecute": false,
    "datasource": {
      "id": "AxiomaDB",
      "isAutoGenerated": false,
      "name": "AxiomaDB",
      "pluginId": "postgres-plugin"
    },
    "dynamicBindingPathList": [
      {
        "key": "body"
      }
    ],
    "name": "q_create_user",
    "pageId": "Dashboard",
    "runBehaviour": "MANUAL",
    "userSetOnLoad": false
  }
}