{
  "gitSyncId": "68f1ea66301c3b6f3e13c5f4_3885d65a-5e43-4630-bf99-d4b33ad1fca4",
  "id": "Dashboard_wa_send",
  "pluginId": "restapi-plugin",
  "pluginType": "API",
  "unpublishedAction": {
    "actionConfiguration": {
      "autoGeneratedHeaders": [
        {
          "key": "content-type",
          "value": "application/json"
        }
      ],
      "body": "{\n  \"to\": \"{{ String(this.params.to || appsmith.store.ownerPhone || InputOwnerPhone?.text || '+34632803533')\n            .replace(/^whatsapp:/,'')\n            .replace(/\\D/g,'') }}\",\n  \"contentSid\": \"{{ String(this.params.contentSidOverride || this.params.contentSid || 'HX3b91ea6167d412d8eacc07312603e58a') }}\",\n  \"contentSidOverride\": \"{{ String(this.params.contentSidOverride || this.params.contentSid || 'HX3b91ea6167d412d8eacc07312603e58a') }}\",\n  \"contentLanguage\": \"es\",\n  \"templateVars\": {{ this.params.templateVars || { \"1\":\"Cliente\", \"2\":\"VIP\", \"3\":\"€ 0\", \"4\": moment().format(\"DD/MM/YYYY\"), \"5\":\"000000\", \"6\":\"10\" } }},\n  \"forceTemplate\": true,\n  \"disableTextFallback\": true\n}\n",
      "bodyFormData": [],
      "encodeParamsToggle": true,
      "formData": {
        "apiContentType": "application/json"
      },
      "headers": [
        {
          "key": "Authorization",
          "value": "Bearer {{ appsmith.store.jwt }}"
        },
        {
          "key": "X-Business-Id",
          "value": "{{ appsmith.store.businessId }}"
        }
      ],
      "httpMethod": "POST",
      "httpVersion": "HTTP11",
      "paginationType": "NONE",
      "path": "/api/wa/send",
      "pluginSpecifiedTemplates": [
        {
          "value": true
        }
      ],
      "queryParameters": [],
      "timeoutInMillisecond": 10000
    },
    "confirmBeforeExecute": false,
    "datasource": {
      "id": "WhatsApp_ok",
      "isAutoGenerated": false,
      "name": "WhatsApp_ok",
      "pluginId": "restapi-plugin"
    },
    "dynamicBindingPathList": [
      {
        "key": "body"
      },
      {
        "key": "headers[0].value"
      },
      {
        "key": "headers[1].value"
      }
    ],
    "name": "wa_send",
    "pageId": "Dashboard",
    "runBehaviour": "MANUAL",
    "userSetOnLoad": false
  }
}