{
  "gitSyncId": "68f1ea66301c3b6f3e13c5f4_7fe344a8-bf58-4ff6-912b-eb5929cb5421",
  "id": "Staff_Mobile_JS_ServiceVisitFlow_Staff.confirmService",
  "pluginId": "js-plugin",
  "pluginType": "JS",
  "unpublishedAction": {
    "actionConfiguration": {
      "encodeParamsToggle": true,
      "jsArguments": [],
      "paginationType": "NONE",
      "timeoutInMillisecond": 10000
    },
    "collectionId": "Staff_Mobile_JS_ServiceVisitFlow_Staff",
    "confirmBeforeExecute": false,
    "datasource": {
      "isAutoGenerated": false,
      "name": "UNUSED_DATASOURCE",
      "pluginId": "js-plugin"
    },
    "dynamicBindingPathList": [
      {
        "key": "body"
      }
    ],
    "fullyQualifiedName": "JS_ServiceVisitFlow_Staff.confirmService",
    "name": "confirmService",
    "pageId": "Staff_Mobile",
    "runBehaviour": "MANUAL",
    "userSetOnLoad": false
  }
}