{
  "gitSyncId": "68f1ea66301c3b6f3e13c5f4_429feb13-5d8e-46f8-be21-2f66c54ec488",
  "id": "Dashboard_JS_BondPayHelper.getVipTrafficLight",
  "pluginId": "js-plugin",
  "pluginType": "JS",
  "unpublishedAction": {
    "actionConfiguration": {
      "encodeParamsToggle": true,
      "jsArguments": [
        {
          "name": "customerId"
        },
        {
          "name": "planId"
        }
      ],
      "paginationType": "NONE",
      "timeoutInMillisecond": 10000
    },
    "collectionId": "Dashboard_JS_BondPayHelper",
    "confirmBeforeExecute": false,
    "datasource": {
      "isAutoGenerated": false,
      "name": "UNUSED_DATASOURCE",
      "pluginId": "js-plugin"
    },
    "dynamicBindingPathList": [
      {
        "key": "body"
      }
    ],
    "fullyQualifiedName": "JS_BondPayHelper.getVipTrafficLight",
    "name": "getVipTrafficLight",
    "pageId": "Dashboard",
    "runBehaviour": "MANUAL",
    "userSetOnLoad": false
  }
}