{
  "animateLoading": true,
  "bottomRow": 115,
  "capSide": 0,
  "capType": "nc",
  "dividerColor": "#858282",
  "dynamicBindingPathList": [],
  "isLoading": false,
  "isVisible": true,
  "key": "8w2rxbckuy",
  "leftColumn": 1,
  "minWidth": 450,
  "mobileBottomRow": 86,
  "mobileLeftColumn": 13,
  "mobileRightColumn": 33,
  "mobileTopRow": 82,
  "needsErrorInfo": false,
  "orientation": "horizontal",
  "originalBottomRow": 115,
  "originalTopRow": 111,
  "parentColumnSpace": 19.3046875,
  "parentId": "szg8flz04n",
  "parentRowSpace": 10,
  "renderMode": "CANVAS",
  "responsiveBehavior": "fill",
  "rightColumn": 64,
  "strokeStyle": "solid",
  "thickness": 2,
  "topRow": 111,
  "type": "DIVIDER_WIDGET",
  "version": 1,
  "widgetId": "1t9hmw4600",
  "widgetName": "Divider4"
}